Workbook

Sheet Project_FactSheet
A1: Project Name: | B1: Powering Sudan's Agriculture: Renewable Water Solutions for Sustainable Future
A2: Award No: | B2: Award No: 1527487 (457)
A3: Donor: | B3: Kuwait Fund for Arab Economic Development (KFAED) 013848
A4: Total budget: | B4: 2000000
A5: Start date: | B5: 45962
A6: End date: | B6: 46507
A7: Duration: | B7: 18 months
A8: Target locations: | B8: White Nile, Al Jazeera, Kassala, Red Sea
A9: Implementing Partners: | B9: NA
A10: Last update to tracker: | B10: 46099

Sheet NKuwait_Tracker
A1: Outcome | B1: Output | C1: Activity | D1: Target | E1: T_WhiteNile | F1: WhiteNile_Actual | G1: T_AlJazeera | H1: AlJazeera_Actual | I1: T_Kassala | J1: Kassala_Actual | K1: T_RedSea | L1: RedSea_Actual | M1: Actual_Total | N1: Comment_18.03
A2: To enhance agricultural productivity, water security, and rural livelihoods in Sudan through sustainable solar-powered irrigation, and improved water infrastructure for smallholder farmers. | B2: Output 1: Improved Access to Affordable and Sustainable Water for Irrigation | C2: Activity 1.1: Install 50 solar-powered water pumps of different capacity based on the existing irrigation structures for irrigation based on the feasibility assessment/study. | D2: 50 | E2: 14 | F2: 10 | G2: 30 | H2: 10 | I2: 3 | J2: 0 | K2: 3 | L2: 0 | N2: 10 in WN; 10 in Gazeera; identified and works ongoing
C3: Activity 1.2 Training of 500 small holder farmers on efficient water management techniques including Solar PV-Operation and Maintenance (O&M). | D3: 500 | E3: 140 | G3: 300 | I3: 30 | K3: 30 | N3: Training after the formation of the association; 10 will be trained in each association/water pump; each association has 10; due to size of water pump capacity, can only support 10-20 farmers
C4: Activity 1.3: Establish/reactivate 50 community-based water user associations varies depending on the existing schemes and farmers associations and cost recovery mechanisms to enhance sustainable and equitable water distribution and management. | D4: 50 | E4: 14 | G4: 30 | I4: 3 | K4: 3 | N4: Linked with solar pump; 1.1 which will be trained
B5: Output 2: Rehabilitated Irrigation Infrastructure for Sustainable Water Management | C5: Activity 2.1: Conduct assessments to identify and prioritize small-scale irrigation infrastructure in need of rehabilitation. | D5: 50 | E5: 14 | G5: 30 | I5: 3 | K5: 3 | N5: Assessment done in November for 20 pumps and 8 canals; scale of impact area of damaged canals to revive maximum agricultural activity; led by Ministry of Agriculture & Irrigation
C6: Activity 2.2: Rehabilitate 28 existing (small) irrigation canals, storage facilities, and water distribution networks to enhance efficiency. | D6: 28 | E6: 11 | G6: 14 | I6: 3 | K6: 3 | N6: 11 done now in WN; 16 in procurement - pending cost estimation and based on which will be able to determine balance for revised target of canals

Sheet Target_Associations
A1: # | B1: State | C1: Locality | D1: Location | E1: GPS coordinates | F1: Association name | G1: Focal Point/ Chair of Association | H1: FP's Phone Number | I1: Farm Area (Feddan) | J1: Number of Association members | K1: Number of beneficiaries
A2: 1 | B2: Al Jazeera | C2: Alhasahesa | D2: Amara Abied | F2: Amara Abied | G2: TajEldien Alshiekh | H2: 0912632133/0128437025 | I2: 10~15 | J2: 580 | L2: 15
A3: 2 | B3: Al Jazeera | C3: Alhasahesa | D3: Arbeji | F3: Arbeji | G3: Ismaiel Altayib Alameen | H3: 911328242 | I3: 10~15 | J3: 131 | L3: 15
A4: 3 | B4: Al Jazeera | C4: Alhasahesa | D4: Wad Alfadni | F4: Khlaw Wad Alfadni | G4: Alkhaliekha Mohammed Alrayh | H4: 912381302 | I4: 10~15 | J4: 62 | L4: 15
A5: 4 | B5: Al Jazeera | C5: Greater Madani | D5: Al-danagla | F5: Aldanagla Collaboration | G5: Alfatih Babikr Alamien | H5: 114225880 | I5: 10~15 | J5: 70 | L5: 15
A6: 5 | B6: Al Jazeera | C6: Greater Madani | D6: Fadasi | F6: Fadasi for Vegateable | G6: Izeldien Omar Ahmed | H6: 916062473 | I6: 10~15 | J6: 70 | L6: 15
A7: 6 | B7: Al Jazeera | C7: AlKamleen | D7: Alkasmber | F7: Kasamber | G7: Mohammed Babikir Alameen | H7: 912860263/0122323603 | I7: 20~30 | J7: 75 | L7: 30
A8: 7 | B8: Al Jazeera | C8: AlKamleen | D8: Al Bashagra | F8: Al Bashagra Collaboration | G8: Mustafa Eltayib | H8: 917322341 | I8: 20~30 | J8: 180 | L8: 30
A9: 8 | B9: Al Jazeera | C9: AlKamleen | D9: Albageir | F9: Collaboration for Friut& Vegateble | G9: Bashier Suliman Ahmed | H9: 0912455272/0113102852 | I9: 20~30 | J9: 2000 | L9: 30
A10: 9 | B10: Al Jazeera | C10: Sourthen of Algazira | D10: Diem Almashaikha | F10: Diem Almashaikha | G10: Mergani Alhaj Altoum | H10: 969633336 | I10: 20~30 | J10: 224 | L10: 30
A11: 10 | B11: Al Jazeera | C11: Sourthen of Algazira | D11: Gendal | F11: Gendal | G11: Hamid Algasim Ahmed | H11: 918081392/0123742249 | I11: 20~30 | J11: 364 | L11: 30
A12: 11 | B12: White Nile | C12: Guli | D12: Alhisi | F12: Awllad Saadwen Agriculture | G12: Tag Al-Asfia Hassan | H12: 912271646 | I12: 10~15 | J12: 36 | L12: 15
A13: 12 | B13: White Nile | C13: Guli | D13: Guli | F13: Al-amel Agriculture | G13: Yagoub Mohamed | H13: 923344409 | I13: 10~15 | J13: 30 | L13: 15
A14: 13 | B14: White Nile | C14: Guli | D14: Wad Shamam | F14: Bashier Alkhier Agriculture | G14: Ahmed Altieb Mahala | H14: 966204853 | I14: 10~15 | J14: 49 | L14: 15
A15: 14 | B15: White Nile | C15: Guli | D15: Wad Shamam | F15: Abna Mongash Agriculture | G15: Ahmed Mohamed Musa | H15: 912763627 | I15: 10~15 | J15: 20 | L15: 15
A16: 15 | B16: White Nile | C16: Guli | D16: Rodat Almokhtar | F16: Bahsr Anied Agriculture | G16: Abdelmajied Hassan Ibrahiem | H16: 999908978 | I16: 10~15 | J16: 35 | L16: 15
A17: 16 | B17: White Nile | C17: Ad-Dewaim | D17: Almoselamb | F17: Almoselamb Agriculture | G17: Alzain Abdala Alobadi | H17: 918049906 | I17: 20~30 | J17: 30 | L17: 30
A18: 17 | B18: White Nile | C18: Ad-Dewaim | D18: Almekefi | F18: Almekefi Agriculture | G18: Abelhafeez Mahmoud | H18: 912491004 | I18: 20~30 | J18: 30 | L18: 30
A19: 18 | B19: White Nile | C19: Ad-Dewaim | D19: Um Lahum | F19: Um Lahum Agriculture | G19: Alkhir Hassan Khalifa | H19: 913252529 | I19: 20~30 | J19: 30 | L19: 30
A20: 19 | B20: White Nile | C20: Ad-Dewaim | D20: Elmeneedrip | F20: Elmeneedrip Agriculture | G20: Basheer Abelrahim Ali | H20: 963164309 | I20: 20~30 | J20: 30 | L20: 30
A21: 20 | B21: White Nile | C21: Ad-Dewaim | D21: Algardood | F21: Algardood Agriculture | G21: Hamud Ahmed Esmaeel | H21: 912519401 | I21: 20~30 | J21: 30 | L21: 30
J22: =SUM(J2:J21) -> 4076
L23: =SUM(L2:L21) -> 450

Sheet Weekly_Updates
A1: Week | B1: Update
A2: 28th Dec to 31st Dec | B2: 5. New Kuwait Project: • A coordination meeting was held with the Ministry of Agriculture to identify locations for irrigation pumps. • Targeted locations were shared by the Ministry of Agriculture. N) White Nile State: Water initiative has officially commenced with the handover of 10 sites: • 8 sites for Nile pumps serving agricultural cooperatives • 2 sites for the rehabilitation of agricultural channels The companies on the ground have started implementing the project.
A4: 4th Jan to 8th Jan | B4: New Kuwait Project (Hewa Co.) – 2 new water yards • The two sites (Alsawarda & Umm Bashim) have been handed over to the contractor. 4- New Kuwait-Funded Project - Gazira & Sinnar • The handover of agricultural irrigation pumps for ten (10) sites successfully completed. E) White Nile State: Water initiative has officially commenced with the handover of 10 sites: • 8 sites for Nile pumps serving agricultural cooperatives • 2 sites for the rehabilitation of agricultural channels The companies on the ground have started implementing the project.
A5: 11th Jan to 15th Jan | B5: New Kuwait Project (Hewa Co.) – 2 new water yards - River Nile • the contractor conducted the geophysical study and started mobilizing the drilling rig and materials to the site 4- New Kuwait-Funded Project - Gazir & Sinanr • The handover of agricultural irrigation pumps for ten (10) sites successfully completed.
A6: 18th Jan to 22nd Jan | B6: New Kuwait Project (Hewa Co.) – 2 new water yards • sites have been handed over to the contractor. And mobilization and preparation of the sites are ongoing New Kuwait-Funded Project – Al Gazira State • Samples of materials have been submitted for approval.
A7: 25th Jan to 29th Jan | B7: New Kuwait Project (Hewa Co.) – 2 new water yards • Drilling rig will arrive today to the site and starts drilling next week. New Kuwait Project- Gazira State • Samples of materials have been approved.
A9: 1st Feb to 5th Feb | B9: New Kuwait Project (Hewa Co.) – 2 new water yards - River Nile • Drilling rig arrived at the site and started drilling.
A10: 8th Feb to 12th Feb
A11: 15th Feb to 19th Feb
A12: 22nd Feb to 26th Feb
A14: 1st Mar to 5th Mar | B14: New Kuwait Project • Provision of ten (10) solar agricultural pumps: the supplier has not yet commenced implementation activities.
A15: 8th Mar to 12th Mar | B15: New Kuwait Project • Provision of ten (10) solar agricultural pumps: the supplier has not yet commenced implementation activities.
A16: 15th Mar to 19th Mar | B16: New Kuwait Project - Powering Sudan's Agriculture: White Nile State: • Provision of ten (10) solar agricultural pumps: the Solar items have been transported to the state • Rehabilitation of 11 Canals: 86% completion of the civil work Gezira State: • Provision of ten (10) solar agricultural pumps: Road permit was issued to trasoport the solar items to state. • Rehabilitation of 16 Canals: under tendering process
A17: 22nd Mar to 26th Mar | B17: • Joint meeting with the Ministry of Production was organized to discuss progress on the rehabilitation of 6 canals at the Gash Scheme • Cost for geophysical survey which was estimated at SDG 16M have been absorbed by State Government. • Joint meeting was convened with Minister of Agriculture to solicit Government support to expediate the process to start the canal rehabilitation. Government promised to absorb some of the cost. . New Kuwait Project # Provision of ten (10) solar agricultural pumps: the supplier has not yet commenced implementation activities. # Contractors completed site visits for bid preparation related to the South Gezira canal rehabilitation project on March 20.
A18: 29th Mar to 2nd Apr | B18: Kuwait 2 Project • A joint engineering team from the Ministry of Agriculture and the Physical Infrastructure are currently finalizing plans to conduct geophysical surveys for the rehabilitation of 6 canals in Kassala State. New Kuwait Project • Provision of ten (10) solar agricultural pumps: The supplier has not yet commenced implementation activities.

Sheet WaterPumps
A1: No. | B1: State | C1: Locality | D1: Location of the water pump | E1: Type of Water Intervention | F1: Site Coordinates | G1: Farm area (Feddan) | H1: Pumping Setting Depth (F) | I1: Pump Selection Type & Model | J1: Nominal Solar Power (kWp) | K1: Number of Panels | L1: N. of hours it operates on solar system | M1: Water production rate per hour ((m³/hr) | N1: Water productivity rate (m³/day) | O1: Number of beneficiaries of water stations (persons) | P1: Status | Q1: Ready for Handover | R1: Handed Over | S1: Handover Date
A2: 1 | B2: Gezira | C2: Alhasahesa | D2: Amara Abied | E2: Solarized Irrigation Pump | G2: 10~15 | H2: N/A | I2: PSK3-7 CS-G100-17/2 | J2: 11.9 | K2: 17 | L2: 8 | M2: 100 | N2: 500 | O2: =Target_Associations!J2 -> 580 | P2: on going
A3: =A2+1 -> 2 | B3: Gezira | C3: Alhasahesa | D3: Arbeji | E3: Solarized Irrigation Pump | G3: 10~15 | H3: N/A | I3: PSK3-7 CS-G100-17/3 | J3: 11.9 | K3: 17 | L3: 8 | M3: 100 | N3: 500 | O3: =Target_Associations!J3 -> 131 | P3: on going
A4: =A3+1 -> 3 | B4: Gezira | C4: Alhasahesa | D4: Wad Alfadni | E4: Solarized Irrigation Pump | G4: 10~15 | H4: N/A | I4: PSK3-7 CS-G100-17/4 | J4: 11.9 | K4: 17 | L4: 8 | M4: 100 | N4: 500 | O4: =Target_Associations!J4 -> 62 | P4: on going
A5: =A4+1 -> 4 | B5: Gezira | C5: Greater Madani | D5: Al-danagla | E5: Solarized Irrigation Pump | G5: 10~15 | H5: N/A | I5: PSK3-7 CS-G100-17/5 | J5: 11.9 | K5: 17 | L5: 8 | M5: 100 | N5: 500 | O5: =Target_Associations!J5 -> 70 | P5: on going
A6: =A5+1 -> 5 | B6: Gezira | C6: Greater Madani | D6: Fadasi | E6: Solarized Irrigation Pump | G6: 10~15 | H6: N/A | I6: PSK3-7 CS-G100-17/6 | J6: 11.9 | K6: 17 | L6: 8 | M6: 100 | N6: 500 | O6: =Target_Associations!J6 -> 70 | P6: on going
A7: =A6+1 -> 6 | B7: Gezira | C7: AlKamleen | D7: Alkasmber | E7: Solarized Irrigation Pump | G7: 20~30 | H7: N/A | I7: PSK3-15 CS-G150-12.5/4,6 | J7: 23.8 | K7: 34 | L7: 8 | M7: 200 | N7: 1000 | O7: =Target_Associations!J7 -> 75 | P7: on going
A8: =A7+1 -> 7 | B8: Gezira | C8: AlKamleen | D8: Um-Dagrsi | E8: Solarized Irrigation Pump | G8: 20~30 | H8: N/A | I8: PSK3-15 CS-G150-12.5/4,6 | J8: 23.8 | K8: 34 | L8: 8 | M8: 200 | N8: 1000 | O8: =Target_Associations!J8 -> 180 | P8: on going
A9: =A8+1 -> 8 | B9: Gezira | C9: AlKamleen | D9: Albageir | E9: Solarized Irrigation Pump | G9: 20~30 | H9: N/A | I9: PSK3-15 CS-G150-12.5/4,6 | J9: 23.8 | K9: 34 | L9: 8 | M9: 200 | N9: 1000 | O9: =Target_Associations!J9 -> 2000 | P9: on going
A10: =A9+1 -> 9 | B10: Gezira | C10: Sourthen of Algazira | D10: Diem Almashaikha | E10: Solarized Irrigation Pump | G10: 20~30 | H10: N/A | I10: PSK3-15 CS-G150-12.5/4,6 | J10: 23.8 | K10: 34 | L10: 8 | M10: 200 | N10: 1000 | O10: =Target_Associations!J10 -> 224 | P10: on going
A11: =A10+1 -> 10 | B11: Gezira | C11: Sourthen of Algazira | D11: Gendal | E11: Solarized Irrigation Pump | G11: 20~30 | H11: N/A | I11: PSK3-15 CS-G150-12.5/4,6 | J11: 23.8 | K11: 34 | L11: 8 | M11: 200 | N11: 1000 | O11: =Target_Associations!J11 -> 364 | P11: on going
A12: =A11+1 -> 11 | B12: White Nile | C12: Guli | D12: Alhisi | E12: Solarized Irrigation Pump | G12: 10~15 | H12: N/A | I12: PSK3-7 CS-G100-17/2 | J12: 11.9 | K12: 17 | L12: 8 | M12: 100 | N12: 500 | O12: =Target_Associations!J12 -> 36 | P12: on going
A13: =A12+1 -> 12 | B13: White Nile | C13: Guli | D13: Guli | E13: Solarized Irrigation Pump | G13: 10~15 | H13: N/A | I13: PSK3-7 CS-G100-17/3 | J13: 11.9 | K13: 17 | L13: 8 | M13: 100 | N13: 500 | O13: =Target_Associations!J13 -> 30 | P13: on going
A14: =A13+1 -> 13 | B14: White Nile | C14: Guli | D14: Wad Shamam | E14: Solarized Irrigation Pump | G14: 10~15 | H14: N/A | I14: PSK3-7 CS-G100-17/4 | J14: 11.9 | K14: 17 | L14: 8 | M14: 100 | N14: 500 | O14: =Target_Associations!J14 -> 49 | P14: on going
... A21: =A20+1 -> 20 | B21: White Nile | C21: Ad-Dewaim | D21: Algardood | E21: Solarized Irrigation Pump | G21: 20~30 | H21: N/A | I21: PSK3-15 CS-G150-12.5/4,6 | J21: 23.8 | K21: 34 | L21: 8 | M21: 200 | N21: 1000 | O21: =Target_Associations!J21 -> 30 | P21: on going

Sheet Canals
A1: No. | B1: State | C1: Locality | D1: Name of Canals | E1: Site Coordinates | F1: Length (m) | G1: SOW | H1: Amount of water flowing in the canals (M3) | I1: Number of beneficiaries of water stations (persons) | J1: Status | K1: Ready for Handover | L1: Handed Over | M1: Handover Date
A2: 1 | B2: White Nile | C2: Guli | D2: Dakhla main canal | E2: 13.592920 N 32.498924 E | F2: 4190 | G2: Rehabilitation irrigation canals of Dakhla main channel | J2: 1
A3: =A2+1 -> 2 | B3: White Nile | C3: Guli | D3: Dakhla canal1 | E3: 13.563492 N 32.498465 E | F3: 1300 | G3: Rehabilitation irrigation canals of branch canal Al-Dakhla, 1 | J3: 1
A4: =A3+1 -> 3 | B4: White Nile | C4: Guli | D4: Dakhla canal 2 | E4: 13.579376 N 32.498351 E | F4: 3000 | G4: Rehabilitation irrigation canals of branch canal Al-Dakhla, 2 | J4: 1
A5: =A4+1 -> 4 | B5: White Nile | C5: Guli | D5: Dakhla canal 3 | E5: 13.558205 N 32.498500 E | F5: 1280 | G5: Rehabilitation irrigation canals of branch canal Al-Dakhla, 3 | J5: 1
A6: =A5+1 -> 5 | B6: White Nile | C6: Guli | D6: Dakhla canal 4 | E6: 13.591984 N 32.498705 E | F6: 1680 | G6: Rehabilitation irrigation canals of branch canal Al-Dakhla, 4 | J6: 1
A7: =A6+1 -> 6 | B7: White Nile | C7: Guli | D7: Safa Main canal | E7: 13.620988 N 32.525441 E | F7: 7974 | G7: Rehabilitation irrigation canals of Al-Safa, main channel | J7: 1
A8: =A7+1 -> 7 | B8: White Nile | C8: Guli | D8: Safa canal 1 | E8: 13.588257 N 32.496598 E | F8: 2020 | G8: Rehabilitation irrigation canals of branch canal Al-Safa, 1 | J8: 1
A9: =A8+1 -> 8 | B9: White Nile | C9: Guli | D9: Safa canal 2 | E9: 13.576706 N 32.484732 E | F9: 1800 | G9: Rehabilitation irrigation canals of branch canal Al-Safa, 2 | J9: 1
A10: =A9+1 -> 9 | B10: White Nile | C10: Guli | D10: Safa canal 3 | E10: 13.571250 N 32.484653 E | F10: 1790 | G10: Rehabilitation irrigation canals of branch canal Al-Safa, 3 | J10: 1
A11: =A10+1 -> 10 | B11: White Nile | C11: Guli | D11: Safa canal 4 | E11: 13.574022 N 32.484747 E | F11: 1610 | G11: Rehabilitation irrigation canals of branch canal Al-Safa, 4 | J11: 1
A12: =A11+1 -> 11 | B12: White Nile | C12: Guli | D12: Safa canal 5 | E12: 13.574109 N 32.484754 E | F12: 700 | G12: Rehabilitation irrigation canals of branch canal Al-Safa, 5 | J12: 1
A13: 12 | B13: Kassala | C13: Kassala | D13: Fota Canal | E13: N 15,3021.54 E 36,2129.78 | F13: 1100 | G13: Rehablitation Irrigation Canal | J13: 1
A14: 13 | B14: Kassala | C14: Kassala | D14: Makaly Canal | E14: N 15,4036.47 E 36,2015.05 | F14: 4100 | G14: Rehablitation Irrigation Canal | J14: 1
F16: =SUBTOTAL(9,F2:F14) -> 32544
G17: =F16/1000 -> 32.544
